foxsenseinnovations/__init__.py
foxsenseinnovations/vigil/__init__.py
foxsenseinnovations/vigil/api_manager_django.py
foxsenseinnovations/vigil/api_manager_fast_api.py
foxsenseinnovations/vigil/api_manager_flask.py
foxsenseinnovations/vigil/api_service.py
foxsenseinnovations/vigil/api_service_async.py
foxsenseinnovations/vigil/error_manager.py
foxsenseinnovations/vigil/job_manager.py
foxsenseinnovations/vigil/vigil.py
foxsenseinnovations/vigil/constants/__init__.py
foxsenseinnovations/vigil/constants/route_constants.py
foxsenseinnovations/vigil/enums/__init__.py
foxsenseinnovations/vigil/enums/http_method_enum.py
foxsenseinnovations/vigil/vigil_types/__init__.py
foxsenseinnovations/vigil/vigil_types/api_monitoring_types.py
foxsenseinnovations/vigil/vigil_types/exception_log_types.py
foxsenseinnovations/vigil/vigil_types/job_monitoring_types.py
foxsenseinnovations/vigil/vigil_types/vigil_options_types.py
foxsenseinnovations/vigil/vigil_utils/__init__.py
foxsenseinnovations/vigil/vigil_utils/api_monitoring_utils_django.py
foxsenseinnovations/vigil/vigil_utils/api_monitoring_utils_fast_api.py
foxsenseinnovations/vigil/vigil_utils/api_monitoring_utils_flask.py
foxsenseinnovations/vigil/vigil_utils/common_utils.py
foxsenseinnovations_vigil-1.1.6.dist-info/METADATA
foxsenseinnovations_vigil-1.1.6.dist-info/WHEEL
foxsenseinnovations_vigil-1.1.6.dist-info/top_level.txt
foxsenseinnovations_vigil-1.1.6.dist-info/RECORD
