Metadata-Version: 2.2
Name: foxsenseinnovations.vigil
Version: 1.1.6
Summary: Official SDK for Vigil - A comprehensive solution for all your monitoring requirements, including exceptions, jobs, APIs, and website availability
License: ISC
Requires-Dist: setuptools
Requires-Dist: requests
Requires-Dist: werkzeug
Requires-Dist: starlette
Dynamic: description
Dynamic: description-content-type
Dynamic: license
Dynamic: requires-dist
Dynamic: summary
